django_cache_mock/__init__.py
django_cache_mock/backends/__init__.py
django_cache_mock/backends/memcached.py
django_cache_mock/backends/redis.py
django_cache_mock/mock.py
django_cache_mock-0.0.3.dist-info/WHEEL
django_cache_mock-0.0.3.dist-info/LICENSE
django_cache_mock-0.0.3.dist-info/METADATA
django_cache_mock-0.0.3.dist-info/RECORD
