Metadata-Version: 2.1
Name: django-cache-mock
Version: 0.0.3
Summary: 
Author: Iuri de Silvio
Author-email: iurisilvio@gmail.com
Requires-Python: >=3.8,<4.0
Classifier: Programming Language :: Python :: 3
Classifier: Programming Language :: Python :: 3.8
Classifier: Programming Language :: Python :: 3.9
Classifier: Programming Language :: Python :: 3.10
Classifier: Programming Language :: Python :: 3.11
Provides-Extra: django-redis
Provides-Extra: fakeredis
Provides-Extra: mockcache
Provides-Extra: redislite
Requires-Dist: django (>=3,<5)
Requires-Dist: django-redis ; extra == "django-redis"
Requires-Dist: fakeredis ; extra == "fakeredis"
Requires-Dist: mockcache3 ; extra == "mockcache"
Requires-Dist: redislite ; extra == "redislite"
